mouselink/__init__.py
mouselink/comms.py
mouselink/mouselink.py
mouselink/pack.py
mouselink-1.0.2.dist-info/METADATA
mouselink-1.0.2.dist-info/WHEEL
mouselink-1.0.2.dist-info/RECORD
