Metadata-Version: 2.4
Name: mouselink
Version: 1.0.2
Summary: Python project that emulates Scratch Link, and allows communication between Scratch and Python.
Project-URL: Homepage, https://github.com/minniesBaa/mouselink
Author-email: minniesBaa <contact@themice.org>
License-Expression: MIT
Classifier: Operating System :: OS Independent
Classifier: Programming Language :: Python :: 3
Requires-Python: >=3.9
Requires-Dist: websockets==15.0.1
